[
    {
        "image": "https://blogdesuperheroes.es/wp-content/plugins/BdSGallery/BdSGaleria/61426.jpg",
        "year": "2018",
        "title": "Pantera negra",
        "punctuation": "3,7",
        "duration": "2h 14m",
        "quality": "HD"
    },
    {
        "image": "https://comoacaba.com/wp-content/uploads/2019/12/v95lURdIFz4A6nqD7pcwv4IWj8H.jpg",
        "year": "2018",
        "title": "Halloween",
        "punctuation": "3,3",
        "duration": "1h 46m",
        "quality": "HD"
    },
    {
        "image": "https://i.pinimg.com/originals/e7/12/d0/e712d01ea44e1b455451b3159bfe159a.jpg",
        "year": "2013",
        "title": "Star Trek Into Darkness",
        "punctuation": "3,9",
        "duration": "2h 12m",
        "quality": "HD"
    }
]